seedboxsync/__init__.py
seedboxsync/main.py
seedboxsync/controllers/__init__.py
seedboxsync/controllers/base.py
seedboxsync/controllers/clean.py
seedboxsync/controllers/search.py
seedboxsync/controllers/stats.py
seedboxsync/controllers/sync.py
seedboxsync/core/__init__.py
seedboxsync/core/db.py
seedboxsync/core/exc.py
seedboxsync/core/init_defaults.py
seedboxsync/core/dao/__init__.py
seedboxsync/core/dao/download.py
seedboxsync/core/dao/lock.py
seedboxsync/core/dao/model.py
seedboxsync/core/dao/seedboxsync.py
seedboxsync/core/dao/torrent.py
seedboxsync/core/sync/__init__.py
seedboxsync/core/sync/abstract_client.py
seedboxsync/core/sync/sftp_client.py
seedboxsync/core/sync/sync.py
seedboxsync/ext/__init__.py
seedboxsync/ext/ext_bcoding.py
seedboxsync/ext/ext_healthchecks.py
seedboxsync/ext/ext_lock.py
seedboxsync/plugins/__init__.py
seedboxsync-3.3.0.dist-info/entry_points.txt
seedboxsync-3.3.0.dist-info/licenses/LICENSE
seedboxsync-3.3.0.dist-info/WHEEL
seedboxsync-3.3.0.dist-info/METADATA
seedboxsync-3.3.0.dist-info/RECORD
