Metadata-Version: 2.4
Name: seedboxsync
Version: 3.3.0
Summary: Script for sync operations between your NAS and your seedbox
Keywords: seedbox,nas,sync,sftp
Author-email: Guillaume Kulakowski <guillaume@kulakowski.fr>
Requires-Python: >=3.10
License-Expression: GPL-3.0-only
Classifier: Development Status :: 5 - Production/Stable
Classifier: Intended Audience :: System Administrators
Classifier: Topic :: Internet
Classifier: Programming Language :: Python :: 3
Classifier: Environment :: Console
Classifier: Natural Language :: English
Classifier: Operating System :: POSIX
License-File: LICENSE
Requires-Dist: cement>=3.0.14
Requires-Dist: pyyaml
Requires-Dist: colorlog
Requires-Dist: paramiko>=2.12
Requires-Dist: bcoding
Requires-Dist: tabulate
Requires-Dist: peewee>=3.0.0
Requires-Dist: flake8 ; extra == "dev"
Requires-Dist: pytest ; extra == "dev"
Requires-Dist: pytest-cov ; extra == "dev"
Requires-Dist: coverage ; extra == "dev"
Requires-Dist: flit ; extra == "dev"
Requires-Dist: mypy ; extra == "dev"
Requires-Dist: twine ; extra == "dev"
Requires-Dist: cement[cli] ; extra == "dev"
Requires-Dist: mkdocs-material ; extra == "dev"
Project-URL: Documentation, https://llaumgui.github.io/seedboxsync/
Project-URL: Home, https://llaumgui.github.io/seedboxsync/
Project-URL: Source, https://github.com/llaumgui/seedboxsync/
Provides-Extra: dev
